{"name":"Ultrasonic Location Tracking Simulator","tagline":"Ultrasonic Location Tracking Simulator","body":"### Indoor Location Tracking Simulator for Ultrasonic-RF Sensor Systems\r\nThis project provides simulation and visualization tools for indoor location tracking systems using TDoA (Time Difference of Arrival) of ultrasonic and RF signals. \r\n\r\n### Authors and Contributors\r\nKang-Wook Kim(@kangwook), Jihye Kwon, Chang-Gun Lee\r\n","google":"","note":"Don't delete this file! It's used internally to help with page regeneration."}